{"batchIndex":5,"batchImportData":{"src/shared/ui/ConfirmModal.tsx":["src/shared/ui/Button.tsx","src/shared/ui/Icon.tsx"],"src/shared/ui/Icon.tsx":[],"src/shared/ui/IdField.tsx":["src/shared/lib/cn.ts","src/shared/lib/format.ts","src/shared/ui/Icon.tsx","src/shared/ui/Toast.tsx"],"src/shared/ui/IgPostPreview.tsx":["src/shared/ui/Icon.tsx"],"src/shared/ui/PlaceholderScreen.tsx":["src/shared/ui/Chip.tsx","src/shared/ui/Icon.tsx"],"src/shared/ui/primitives.tsx":["src/shared/lib/cn.ts","src/shared/ui/Card.tsx","src/shared/ui/Icon.tsx"],"src/widgets/business-portfolio/ChannelInsights.tsx":["src/entities/insights/optimization.ts","src/features/channel-suggestion-action/AiDraftModal.tsx","src/shared/lib/cn.ts","src/shared/ui/Button.tsx","src/shared/ui/Card.tsx","src/shared/ui/Icon.tsx","src/shared/ui/IgPostPreview.tsx","src/shared/ui/primitives.tsx"],"src/widgets/business-portfolio/CompareBar.tsx":["src/shared/ui/Card.tsx","src/shared/ui/Icon.tsx"],"src/widgets/business-portfolio/Messages.tsx":["lib/instagram-messages.ts","src/shared/lib/cn.ts","src/shared/ui/Card.tsx","src/shared/ui/Icon.tsx","src/widgets/business-portfolio/MessagesPermissionBanner.tsx"],"src/widgets/business-portfolio/MessagesPermissionBanner.tsx":["src/shared/ui/Icon.tsx"],"src/widgets/business-portfolio/Partnerships.tsx":["app/api/instagram/branded-content/route.ts","src/shared/ui/Card.tsx","src/shared/ui/Icon.tsx"],"src/widgets/business-portfolio/PromotedContent.tsx":["src/shared/ui/Card.tsx","src/shared/ui/Icon.tsx"],"src/widgets/business-portfolio/Stories.tsx":["lib/instagram-stories.ts","src/shared/lib/cn.ts","src/shared/ui/Card.tsx","src/shared/ui/Icon.tsx"],"src/widgets/business-portfolio/index.tsx":["lib/facebook-insights.ts","lib/instagram-insights.ts","src/entities/insights/optimization.ts","src/shared/lib/cn.ts","src/widgets/business-portfolio/ChannelInsights.tsx","src/widgets/business-portfolio/CompareBar.tsx","src/widgets/business-portfolio/Messages.tsx","src/widgets/business-portfolio/Partnerships.tsx","src/widgets/business-portfolio/PromotedContent.tsx","src/widgets/business-portfolio/Stories.tsx"],"src/widgets/creative-step/BriefForm.tsx":["src/entities/creative/options.ts","src/shared/lib/cn.ts","src/shared/lib/referenceMaterials.ts","src/shared/ui/Button.tsx","src/shared/ui/Icon.tsx"],"src/widgets/creative-step/ImagePhase.tsx":["src/entities/creative/model.tsx","src/shared/ui/Button.tsx","src/shared/ui/Card.tsx","src/shared/ui/Icon.tsx","src/shared/ui/primitives.tsx","src/widgets/creative-step/AiImageBlock.tsx"],"src/widgets/creative-step/ResultPanel.tsx":["src/entities/creative/options.ts","src/shared/lib/cn.ts","src/shared/ui/Button.tsx","src/shared/ui/Card.tsx","src/shared/ui/Icon.tsx","src/shared/ui/primitives.tsx","src/shared/ui/Skeleton.tsx"],"src/widgets/creative-step/index.tsx":["src/entities/creative/options.ts","src/widgets/creative-step/ImagePhase.tsx","src/widgets/creative-step/InputForm.tsx","src/widgets/creative-step/ResultPanel.tsx"],"src/widgets/facebook/PageSwitcher.tsx":["lib/facebook-pages.ts","src/shared/ui/Icon.tsx"],"src/widgets/launch-step/CampaignSkeletonSuccessCard.tsx":["src/entities/campaign/model.tsx","src/shared/ui/Button.tsx","src/shared/ui/Card.tsx","src/shared/ui/Icon.tsx"],"src/widgets/launch-step/LaunchStatusPanel.tsx":["src/entities/campaign/model.tsx","src/shared/ui/Button.tsx","src/shared/ui/Card.tsx","src/shared/ui/Icon.tsx","src/widgets/launch-step/CampaignSkeletonSuccessCard.tsx","src/widgets/launch-step/LaunchSuccessCard.tsx"],"src/widgets/launch-step/LaunchSuccessCard.tsx":["src/entities/campaign/model.tsx","src/shared/ui/Button.tsx","src/shared/ui/Card.tsx","src/shared/ui/Icon.tsx","src/shared/ui/primitives.tsx"],"src/widgets/onboarding-guard/index.tsx":[],"src/widgets/performance-step/CampaignBar.tsx":["src/entities/campaign/model.tsx","src/entities/creative/options.ts","src/entities/insights/types.ts","src/shared/ui/Button.tsx","src/shared/ui/Card.tsx","src/shared/ui/Icon.tsx","src/shared/ui/primitives.tsx"],"src/widgets/performance-step/ExampleBanner.tsx":["src/shared/lib/cn.ts","src/shared/ui/Card.tsx","src/shared/ui/Icon.tsx"],"src/widgets/performance-step/OptimizationPanel.tsx":["src/entities/insights/optimization.ts","src/shared/lib/format.ts","src/shared/ui/Button.tsx","src/shared/ui/Card.tsx","src/shared/ui/Icon.tsx","src/shared/ui/primitives.tsx"],"src/widgets/post-launch-checklist/index.tsx":["src/entities/campaign/model.tsx","src/shared/ui/Button.tsx","src/shared/ui/Card.tsx","src/shared/ui/Icon.tsx"]},"neighborMap":{"src/shared/ui/ConfirmModal.tsx":[{"path":"src/shared/ui/Button.tsx","batchIndex":2,"symbols":["Button","buttonVariants"]},{"path":"app/(workspace)/campaigns/[id]/page.tsx","batchIndex":9,"symbols":["CampaignDetailPage"]},{"path":"app/(workspace)/connect/page.tsx","batchIndex":2,"symbols":["ConnectPage"]},{"path":"app/(workspace)/instagram/comments/page.tsx","batchIndex":2,"symbols":["CommentsPage"]},{"path":"app/(workspace)/instagram/posts/page.tsx","batchIndex":3,"symbols":["PostsPage"]}],"src/shared/ui/Icon.tsx":[{"path":"src/entities/creative/options.ts","batchIndex":6,"symbols":["TONES","CTAS","IMAGES","TONE_PROMPT_DESC","CTA_LABEL","CTA_META_TYPE","IMAGE_ART","OBJECTIVES_PHASE1","OBJECTIVES_PHASE2","OBJECTIVES_ALL","findObjective","COPY_HOOKS","COPY_HOOK_MAP","findHook","HOOK_RECOMMENDATIONS_BY_OBJECTIVE","recommendedHooks","GOAL_RESULT"]},{"path":"app/(workspace)/campaigns/[id]/page.tsx","batchIndex":9,"symbols":["CampaignDetailPage"]},{"path":"src/widgets/launch-step/index.tsx","batchIndex":7,"symbols":["LaunchStep"]},{"path":"app/(workspace)/create/page.tsx","batchIndex":6,"symbols":["CreatePage"]},{"path":"src/widgets/tournament-setup/index.tsx","batchIndex":1,"symbols":["TournamentSetup"]},{"path":"src/widgets/performance-step/index.tsx","batchIndex":11,"symbols":["PerformanceStep"]},{"path":"app/(workspace)/brand-profile/[id]/edit/page.tsx","batchIndex":3,"symbols":["BrandProfileEditPage"]},{"path":"src/widgets/creative-step/AiImageBlock.tsx","batchIndex":12,"symbols":["AiImageBlock"]},{"path":"src/widgets/launch-step/BoostPostFlow.tsx","batchIndex":7,"symbols":["BoostPostFlow"]},{"path":"app/(workspace)/brand-profile/[id]/page.tsx","batchIndex":3,"symbols":["BrandProfileViewPage"]},{"path":"app/(workspace)/campaigns/page.tsx","batchIndex":9,"symbols":["CampaignsPage"]},{"path":"src/widgets/creative-step/InputForm.tsx","batchIndex":3,"symbols":["InputForm"]},{"path":"app/(workspace)/ab-tests/[id]/page.tsx","batchIndex":1,"symbols":["AbTournamentDetailPage"]},{"path":"app/(workspace)/brand-profile/page.tsx","batchIndex":3,"symbols":["BrandProfilePage"]},{"path":"app/(workspace)/dashboard/page.tsx","batchIndex":9,"symbols":["DashboardPage"]},{"path":"app/(workspace)/instagram/posts/page.tsx","batchIndex":3,"symbols":["PostsPage"]},{"path":"app/(workspace)/library/page.tsx","batchIndex":9,"symbols":["LibraryPage"]},{"path":"src/widgets/launch-step/DestinationField.tsx","batchIndex":7,"symbols":["DestinationField"]},{"path":"app/(workspace)/ab-tests/page.tsx","batchIndex":1,"symbols":["AbTestsPage"]},{"path":"app/(workspace)/billing/page.tsx","batchIndex":9,"symbols":["BillingPage"]},{"path":"app/(workspace)/settings/page.tsx","batchIndex":2,"symbols":["SettingsPage"]},{"path":"src/widgets/goal-intro/index.tsx","batchIndex":7,"symbols":["GoalIntro"]},{"path":"src/widgets/launch-step/BudgetScheduleStep.tsx","batchIndex":7,"symbols":["BudgetScheduleStep"]},{"path":"src/widgets/launch-step/TargetStep.tsx","batchIndex":7,"symbols":["TargetStep"]},{"path":"src/widgets/tournament-setup/ChallengerImageGen.tsx","batchIndex":12,"symbols":["ChallengerImageGen"]},{"path":"app/(workspace)/approvals/page.tsx","batchIndex":2,"symbols":["ApprovalsPage"]},{"path":"app/(workspace)/connect/page.tsx","batchIndex":2,"symbols":["ConnectPage"]},{"path":"app/(workspace)/members/[id]/page.tsx","batchIndex":2,"symbols":["MemberDetailPage"]},{"path":"src/entities/creative/ui/SelectedGoalCard.tsx","batchIndex":6,"symbols":["SelectedGoalCard"]},{"path":"src/widgets/launch-step/CreativePreview.tsx","batchIndex":7,"symbols":["CreativePreview"]},{"path":"src/widgets/launch-step/SummaryCard.tsx","batchIndex":7,"symbols":["SummaryCard"]},{"path":"lib/demo/content.ts","batchIndex":1,"symbols":["DEMO_INPUTS","DEMO_HEADLINES","DEMO_PRIMARY_TEXTS","DEMO_IMAGE_PROMPT","DEMO_IMAGES","DEMO_CTA","DEMO_CREATIVE_RESULT","DEMO_SUGGESTIONS"]},{"path":"src/widgets/launch-step/PlacementKnob.tsx","batchIndex":7,"symbols":["PlacementKnob"]},{"path":"src/widgets/performance-step/AbTestResultCard.tsx","batchIndex":11,"symbols":["AbTestResultCard"]},{"path":"src/widgets/sidebar/index.tsx","batchIndex":1,"symbols":["Sidebar"]},{"path":"src/features/brand-profile/ui/PersonaCard.tsx","batchIndex":3,"symbols":["PersonaCard"]},{"path":"src/features/sop/ui/SopEditModal.tsx","batchIndex":3,"symbols":["SopEditModal"]},{"path":"src/widgets/billing-alert/index.tsx","batchIndex":11,"symbols":["BillingAlertWidget"]},{"path":"src/widgets/launch-step/ConfirmStep.tsx","batchIndex":7,"symbols":["ConfirmStep"]},{"path":"src/widgets/performance-step/DailyTrend.tsx","batchIndex":11,"symbols":["DailyTrend"]},{"path":"app/(workspace)/facebook/posts/page.tsx","batchIndex":2,"symbols":["FacebookPostsPage"]},{"path":"app/(workspace)/members/page.tsx","batchIndex":2,"symbols":["MembersPage"]},{"path":"src/features/brand-profile/ui/CopyReferenceSection.tsx","batchIndex":2,"symbols":["CopyReferenceSection"]},{"path":"src/features/brand-profile/ui/PersonaQuickCreateModal.tsx","batchIndex":3,"symbols":["PersonaQuickCreateModal"]},{"path":"src/features/sop/ui/SopCard.tsx","batchIndex":3,"symbols":["SopCard"]},{"path":"src/widgets/launch-step/ABCreativeKnob.tsx","batchIndex":7,"symbols":["ABCreativeKnob"]},{"path":"src/widgets/launch-step/FrequencyCapKnob.tsx","batchIndex":7,"symbols":["FrequencyCapKnob"]},{"path":"app/(workspace)/instagram/comments/page.tsx","batchIndex":2,"symbols":["CommentsPage"]},{"path":"src/features/brand-profile/ui/IgImportModal.tsx","batchIndex":2,"symbols":["IgImportModal"]},{"path":"src/features/brand-profile/ui/PersonaEditModal.tsx","batchIndex":3,"symbols":["PersonaEditModal"]}],"src/shared/ui/IdField.tsx":[{"path":"src/shared/lib/cn.ts","batchIndex":6,"symbols":["cn"]},{"path":"src/shared/lib/format.ts","batchIndex":11,"symbols":["fmt","fmtKRW","shortDate","campaignGradient","kDate","campaignDateInfo","campaignRunDays","maskId","timeAgo"]},{"path":"src/shared/ui/Toast.tsx","batchIndex":1,"symbols":["ToastProvider","useToast"]},{"path":"app/(workspace)/connect/page.tsx","batchIndex":2,"symbols":["ConnectPage"]},{"path":"app/(workspace)/settings/page.tsx","batchIndex":2,"symbols":["SettingsPage"]}],"src/shared/ui/IgPostPreview.tsx":[{"path":"app/(workspace)/ab-tests/[id]/page.tsx","batchIndex":1,"symbols":["AbTournamentDetailPage"]},{"path":"app/(workspace)/instagram/comments/page.tsx","batchIndex":2,"symbols":["CommentsPage"]},{"path":"app/(workspace)/instagram/posts/page.tsx","batchIndex":3,"symbols":["PostsPage"]},{"path":"src/features/brand-profile/ui/IgImportModal.tsx","batchIndex":2,"symbols":["IgImportModal"]}],"src/shared/ui/PlaceholderScreen.tsx":[{"path":"src/shared/ui/Chip.tsx","batchIndex":11,"symbols":["Chip"]}],"src/shared/ui/primitives.tsx":[{"path":"src/shared/lib/cn.ts","batchIndex":6,"symbols":["cn"]},{"path":"src/shared/ui/Card.tsx","batchIndex":2,"symbols":["Card"]},{"path":"app/(workspace)/approvals/page.tsx","batchIndex":2,"symbols":["ApprovalsPage"]},{"path":"app/(workspace)/campaigns/[id]/page.tsx","batchIndex":9,"symbols":["CampaignDetailPage"]},{"path":"app/(workspace)/campaigns/page.tsx","batchIndex":9,"symbols":["CampaignsPage"]},{"path":"app/(workspace)/create/page.tsx","batchIndex":6,"symbols":["CreatePage"]},{"path":"app/(workspace)/dashboard/page.tsx","batchIndex":9,"symbols":["DashboardPage"]},{"path":"app/(workspace)/library/page.tsx","batchIndex":9,"symbols":["LibraryPage"]},{"path":"app/(workspace)/members/[id]/page.tsx","batchIndex":2,"symbols":["MemberDetailPage"]},{"path":"app/(workspace)/settings/page.tsx","batchIndex":2,"symbols":["SettingsPage"]},{"path":"src/widgets/creative-step/AiImageBlock.tsx","batchIndex":12,"symbols":["AiImageBlock"]},{"path":"src/widgets/creative-step/InputForm.tsx","batchIndex":3,"symbols":["InputForm"]},{"path":"src/widgets/goal-intro/index.tsx","batchIndex":7,"symbols":["GoalIntro"]},{"path":"src/widgets/launch-step/AudienceKnob.tsx","batchIndex":7,"symbols":["AudienceKnob"]},{"path":"src/widgets/launch-step/DetailKnobs.tsx","batchIndex":7,"symbols":["DetailKnobs"]},{"path":"src/widgets/launch-step/FrequencyCapKnob.tsx","batchIndex":7,"symbols":["FrequencyCapKnob"]},{"path":"src/widgets/launch-step/SummaryCard.tsx","batchIndex":7,"symbols":["SummaryCard"]},{"path":"src/widgets/performance-step/KpiGrid.tsx","batchIndex":11,"symbols":["KpiGrid"]}],"src/widgets/business-portfolio/ChannelInsights.tsx":[{"path":"src/entities/insights/optimization.ts","batchIndex":2,"symbols":["suggestChannelOptimizations","suggestIgOptimizations","suggestOptimizations","assessAutomationReadiness"]},{"path":"src/features/channel-suggestion-action/AiDraftModal.tsx","batchIndex":2,"symbols":["AiDraftModal"]},{"path":"src/shared/lib/cn.ts","batchIndex":6,"symbols":["cn"]},{"path":"src/shared/ui/Button.tsx","batchIndex":2,"symbols":["Button","buttonVariants"]},{"path":"src/shared/ui/Card.tsx","batchIndex":2,"symbols":["Card"]},{"path":"app/(workspace)/facebook/page.tsx","batchIndex":2,"symbols":["FacebookInsightsPage"]},{"path":"app/(workspace)/instagram/page.tsx","batchIndex":2,"symbols":["InstagramInsightsPage"]}],"src/widgets/business-portfolio/CompareBar.tsx":[{"path":"src/shared/ui/Card.tsx","batchIndex":2,"symbols":["Card"]}],"src/widgets/business-portfolio/Messages.tsx":[{"path":"lib/instagram-messages.ts","batchIndex":13,"symbols":["IG_INBOX_MOCK","IG_THREAD_MOCK_DEFAULT","getMockThread","getInstagramInbox","getInstagramThread","sendInstagramMessage"]},{"path":"src/shared/lib/cn.ts","batchIndex":6,"symbols":["cn"]},{"path":"src/shared/ui/Card.tsx","batchIndex":2,"symbols":["Card"]},{"path":"app/(workspace)/instagram/messages/page.tsx","batchIndex":2,"symbols":["InstagramMessagesPage"]}],"src/widgets/business-portfolio/Partnerships.tsx":[{"path":"app/api/instagram/branded-content/route.ts","batchIndex":2,"symbols":["GET"]},{"path":"src/shared/ui/Card.tsx","batchIndex":2,"symbols":["Card"]},{"path":"app/(workspace)/instagram/partnerships/page.tsx","batchIndex":2,"symbols":["InstagramPartnershipsPage"]}],"src/widgets/business-portfolio/PromotedContent.tsx":[{"path":"src/shared/ui/Card.tsx","batchIndex":2,"symbols":["Card"]}],"src/widgets/business-portfolio/Stories.tsx":[{"path":"lib/instagram-stories.ts","batchIndex":13,"symbols":["IG_STORIES_MOCK","getInstagramActiveStories"]},{"path":"src/shared/lib/cn.ts","batchIndex":6,"symbols":["cn"]},{"path":"src/shared/ui/Card.tsx","batchIndex":2,"symbols":["Card"]},{"path":"app/(workspace)/instagram/stories/page.tsx","batchIndex":2,"symbols":["InstagramStoriesPage"]}],"src/widgets/business-portfolio/index.tsx":[{"path":"lib/facebook-insights.ts","batchIndex":2,"symbols":["FB_MOCK_GOOD","FB_MOCK_POOR","getFacebookInsights"]},{"path":"lib/instagram-insights.ts","batchIndex":2,"symbols":["IG_MOCK_GOOD","IG_MOCK_POOR","debugInstagramInsights","getInstagramInsights"]},{"path":"src/entities/insights/optimization.ts","batchIndex":2,"symbols":["suggestChannelOptimizations","suggestIgOptimizations","suggestOptimizations","assessAutomationReadiness"]},{"path":"src/shared/lib/cn.ts","batchIndex":6,"symbols":["cn"]}],"src/widgets/creative-step/BriefForm.tsx":[{"path":"src/entities/creative/options.ts","batchIndex":6,"symbols":["TONES","CTAS","IMAGES","TONE_PROMPT_DESC","CTA_LABEL","CTA_META_TYPE","IMAGE_ART","OBJECTIVES_PHASE1","OBJECTIVES_PHASE2","OBJECTIVES_ALL","findObjective","COPY_HOOKS","COPY_HOOK_MAP","findHook","HOOK_RECOMMENDATIONS_BY_OBJECTIVE","recommendedHooks","GOAL_RESULT"]},{"path":"src/shared/lib/cn.ts","batchIndex":6,"symbols":["cn"]},{"path":"src/shared/lib/referenceMaterials.ts","batchIndex":3,"symbols":["useReferenceMaterials","formatBytes"]},{"path":"src/shared/ui/Button.tsx","batchIndex":2,"symbols":["Button","buttonVariants"]},{"path":"src/widgets/creative-step/AiImageBlock.tsx","batchIndex":12,"symbols":["AiImageBlock"]}],"src/widgets/creative-step/ImagePhase.tsx":[{"path":"src/entities/creative/model.tsx","batchIndex":6,"symbols":["INITIAL_CREATIVE_STATE","CreativeStateProvider","useCreativeDraft"]},{"path":"src/shared/ui/Button.tsx","batchIndex":2,"symbols":["Button","buttonVariants"]},{"path":"src/shared/ui/Card.tsx","batchIndex":2,"symbols":["Card"]},{"path":"src/widgets/creative-step/AiImageBlock.tsx","batchIndex":12,"symbols":["AiImageBlock"]}],"src/widgets/creative-step/ResultPanel.tsx":[{"path":"src/entities/creative/options.ts","batchIndex":6,"symbols":["TONES","CTAS","IMAGES","TONE_PROMPT_DESC","CTA_LABEL","CTA_META_TYPE","IMAGE_ART","OBJECTIVES_PHASE1","OBJECTIVES_PHASE2","OBJECTIVES_ALL","findObjective","COPY_HOOKS","COPY_HOOK_MAP","findHook","HOOK_RECOMMENDATIONS_BY_OBJECTIVE","recommendedHooks","GOAL_RESULT"]},{"path":"src/shared/lib/cn.ts","batchIndex":6,"symbols":["cn"]},{"path":"src/shared/ui/Button.tsx","batchIndex":2,"symbols":["Button","buttonVariants"]},{"path":"src/shared/ui/Card.tsx","batchIndex":2,"symbols":["Card"]},{"path":"src/shared/ui/Skeleton.tsx","batchIndex":11,"symbols":["Skeleton"]}],"src/widgets/creative-step/index.tsx":[{"path":"src/entities/creative/options.ts","batchIndex":6,"symbols":["TONES","CTAS","IMAGES","TONE_PROMPT_DESC","CTA_LABEL","CTA_META_TYPE","IMAGE_ART","OBJECTIVES_PHASE1","OBJECTIVES_PHASE2","OBJECTIVES_ALL","findObjective","COPY_HOOKS","COPY_HOOK_MAP","findHook","HOOK_RECOMMENDATIONS_BY_OBJECTIVE","recommendedHooks","GOAL_RESULT"]},{"path":"src/widgets/creative-step/InputForm.tsx","batchIndex":3,"symbols":["InputForm"]},{"path":"app/(workspace)/create/page.tsx","batchIndex":6,"symbols":["CreatePage"]}],"src/widgets/facebook/PageSwitcher.tsx":[{"path":"lib/facebook-pages.ts","batchIndex":2,"symbols":["FB_PAGES_MOCK","getFacebookManagedPages"]},{"path":"app/(workspace)/facebook/page.tsx","batchIndex":2,"symbols":["FacebookInsightsPage"]},{"path":"app/(workspace)/facebook/posts/page.tsx","batchIndex":2,"symbols":["FacebookPostsPage"]}],"src/widgets/launch-step/CampaignSkeletonSuccessCard.tsx":[{"path":"src/entities/campaign/model.tsx","batchIndex":6,"symbols":["abVariantLabel","INITIAL_LAUNCH_STATE","LaunchStateProvider","useLaunchDraft"]},{"path":"src/shared/ui/Button.tsx","batchIndex":2,"symbols":["Button","buttonVariants"]},{"path":"src/shared/ui/Card.tsx","batchIndex":2,"symbols":["Card"]}],"src/widgets/launch-step/LaunchStatusPanel.tsx":[{"path":"src/entities/campaign/model.tsx","batchIndex":6,"symbols":["abVariantLabel","INITIAL_LAUNCH_STATE","LaunchStateProvider","useLaunchDraft"]},{"path":"src/shared/ui/Button.tsx","batchIndex":2,"symbols":["Button","buttonVariants"]},{"path":"src/shared/ui/Card.tsx","batchIndex":2,"symbols":["Card"]},{"path":"src/widgets/launch-step/BoostPostFlow.tsx","batchIndex":7,"symbols":["BoostPostFlow"]},{"path":"src/widgets/launch-step/index.tsx","batchIndex":7,"symbols":["LaunchStep"]}],"src/widgets/launch-step/LaunchSuccessCard.tsx":[{"path":"src/entities/campaign/model.tsx","batchIndex":6,"symbols":["abVariantLabel","INITIAL_LAUNCH_STATE","LaunchStateProvider","useLaunchDraft"]},{"path":"src/shared/ui/Button.tsx","batchIndex":2,"symbols":["Button","buttonVariants"]},{"path":"src/shared/ui/Card.tsx","batchIndex":2,"symbols":["Card"]}],"src/widgets/onboarding-guard/index.tsx":[{"path":"app/(workspace)/layout.tsx","batchIndex":1,"symbols":["viewport","WorkspaceLayout"]},{"path":"app/(workspace)/settings/page.tsx","batchIndex":2,"symbols":["SettingsPage"]},{"path":"app/onboarding/page.tsx","batchIndex":2,"symbols":["OnboardingPage"]}],"src/widgets/performance-step/CampaignBar.tsx":[{"path":"src/entities/campaign/model.tsx","batchIndex":6,"symbols":["abVariantLabel","INITIAL_LAUNCH_STATE","LaunchStateProvider","useLaunchDraft"]},{"path":"src/entities/creative/options.ts","batchIndex":6,"symbols":["TONES","CTAS","IMAGES","TONE_PROMPT_DESC","CTA_LABEL","CTA_META_TYPE","IMAGE_ART","OBJECTIVES_PHASE1","OBJECTIVES_PHASE2","OBJECTIVES_ALL","findObjective","COPY_HOOKS","COPY_HOOK_MAP","findHook","HOOK_RECOMMENDATIONS_BY_OBJECTIVE","recommendedHooks","GOAL_RESULT"]},{"path":"src/entities/insights/types.ts","batchIndex":11,"symbols":[]},{"path":"src/shared/ui/Button.tsx","batchIndex":2,"symbols":["Button","buttonVariants"]},{"path":"src/shared/ui/Card.tsx","batchIndex":2,"symbols":["Card"]},{"path":"src/widgets/performance-step/index.tsx","batchIndex":11,"symbols":["PerformanceStep"]}],"src/widgets/performance-step/ExampleBanner.tsx":[{"path":"src/shared/lib/cn.ts","batchIndex":6,"symbols":["cn"]},{"path":"src/shared/ui/Card.tsx","batchIndex":2,"symbols":["Card"]},{"path":"src/widgets/performance-step/index.tsx","batchIndex":11,"symbols":["PerformanceStep"]}],"src/widgets/performance-step/OptimizationPanel.tsx":[{"path":"src/entities/insights/optimization.ts","batchIndex":2,"symbols":["suggestChannelOptimizations","suggestIgOptimizations","suggestOptimizations","assessAutomationReadiness"]},{"path":"src/shared/lib/format.ts","batchIndex":11,"symbols":["fmt","fmtKRW","shortDate","campaignGradient","kDate","campaignDateInfo","campaignRunDays","maskId","timeAgo"]},{"path":"src/shared/ui/Button.tsx","batchIndex":2,"symbols":["Button","buttonVariants"]},{"path":"src/shared/ui/Card.tsx","batchIndex":2,"symbols":["Card"]},{"path":"src/widgets/performance-step/index.tsx","batchIndex":11,"symbols":["PerformanceStep"]}],"src/widgets/post-launch-checklist/index.tsx":[{"path":"src/entities/campaign/model.tsx","batchIndex":6,"symbols":["abVariantLabel","INITIAL_LAUNCH_STATE","LaunchStateProvider","useLaunchDraft"]},{"path":"src/shared/ui/Button.tsx","batchIndex":2,"symbols":["Button","buttonVariants"]},{"path":"src/shared/ui/Card.tsx","batchIndex":2,"symbols":["Card"]},{"path":"app/(workspace)/create/page.tsx","batchIndex":6,"symbols":["CreatePage"]}]}}